CHANGES.txt
DEPENDENCES.txt
README.txt
setup.py
src/ng/__init__.py
src/ng.lib.egg-info/PKG-INFO
src/ng.lib.egg-info/SOURCES.txt
src/ng.lib.egg-info/dependency_links.txt
src/ng.lib.egg-info/namespace_packages.txt
src/ng.lib.egg-info/not-zip-safe
src/ng.lib.egg-info/requires.txt
src/ng.lib.egg-info/top_level.txt
src/ng/lib/__init__.py
src/ng/lib/containconstraint.py
src/ng/lib/dynamicdefault.py
src/ng/lib/editannotationnotify.py
src/ng/lib/indexvocabulary.py
src/ng/lib/interface.py
src/ng/lib/interfaces.py
src/ng/lib/ng.lib.txt
src/ng/lib/objectwidget.py
src/ng/lib/orderinformation.py
src/ng/lib/registryvocabulary.py
src/ng/lib/simplevocabulary.py
src/ng/lib/utilityvocabulary.py
src/ng/lib/viewletbase.py
src/ng/lib/walk.py