Metadata-Version: 1.0
Name: ng.lib
Version: 0.0.8
Summary: Library of small but useful modules for Zope
Home-page: http://dreambot.ru/dreambotzope3releases/ng.lib
Author: Andrey Orlov
Author-email: dbdt@dreambot.ru
License: GPL v2.1
Platform: UNKNOWN
Classifier: Environment :: Web Environment
Classifier: Intended Audience :: Developers
Classifier: License :: OSI Approved :: GNU General Public License (GPL)
Classifier: Programming Language :: Python
Classifier: Operating System :: OS Independent
Classifier: Topic :: Internet :: WWW/HTTP
Classifier: Framework :: Zope3
